asgi_sessions/__init__.py
asgi_sessions/py.typed
asgi_sessions-1.3.0.dist-info/licenses/LICENSE
asgi_sessions-1.3.0.dist-info/METADATA
asgi_sessions-1.3.0.dist-info/WHEEL
asgi_sessions-1.3.0.dist-info/top_level.txt
asgi_sessions-1.3.0.dist-info/RECORD
