Metadata-Version: 2.4
Name: asgi-sessions
Version: 1.3.0
Summary: Signed Cookie-Based HTTP sessions for ASGI applications
Author-email: Kirill Klenov <horneds@gmail.com>
License: MIT License
Project-URL: homepage, https://github.com/klen/asgi-sessions
Project-URL: repository, https://github.com/klen/asgi-sessions
Keywords: asyncio,trio,asgi,asgi sessions,cookies
Classifier: Topic :: Software Development :: Internationalization
Classifier: Development Status :: 5 - Production/Stable
Classifier: Intended Audience :: Developers
Classifier: License :: OSI Approved :: MIT License
Classifier: Programming Language :: Python
Classifier: Programming Language :: Python :: 3
Classifier: Programming Language :: Python :: 3.10
Classifier: Programming Language :: Python :: 3.11
Classifier: Programming Language :: Python :: 3.12
Classifier: Programming Language :: Python :: 3.13
Classifier: Programming Language :: Python :: 3.14
Classifier: Topic :: Internet :: WWW/HTTP
Classifier: Framework :: AsyncIO
Classifier: Framework :: Trio
Requires-Python: >=3.10
License-File: LICENSE
Requires-Dist: asgi-tools>=0.71.0
Provides-Extra: tests
Requires-Dist: cryptography; extra == "tests"
Requires-Dist: PyJWT; extra == "tests"
Requires-Dist: pytest; extra == "tests"
Requires-Dist: pytest-aio[curio,trio]; extra == "tests"
Requires-Dist: pytest-mypy; extra == "tests"
Requires-Dist: types-orjson; extra == "tests"
Requires-Dist: types-ujson; extra == "tests"
Requires-Dist: ruff; extra == "tests"
Provides-Extra: example
Requires-Dist: uvicorn; extra == "example"
Provides-Extra: dev
Requires-Dist: bump2version; extra == "dev"
Requires-Dist: tox; extra == "dev"
Requires-Dist: pre-commit; extra == "dev"
Provides-Extra: fernet
Requires-Dist: cryptography; extra == "fernet"
Provides-Extra: jwt
Requires-Dist: PyJWT; extra == "jwt"
Dynamic: license-file
